openbb_equity/__init__.py
openbb_equity/calendar/__init__.py
openbb_equity/calendar/calendar_router.py
openbb_equity/compare/__init__.py
openbb_equity/compare/compare_router.py
openbb_equity/darkpool/__init__.py
openbb_equity/darkpool/darkpool_router.py
openbb_equity/discovery/__init__.py
openbb_equity/discovery/discovery_router.py
openbb_equity/equity_router.py
openbb_equity/equity_views.py
openbb_equity/estimates/__init__.py
openbb_equity/estimates/estimates_router.py
openbb_equity/fundamental/__init__.py
openbb_equity/fundamental/fundamental_router.py
openbb_equity/ownership/__init__.py
openbb_equity/ownership/ownership_router.py
openbb_equity/price/__init__.py
openbb_equity/price/price_router.py
openbb_equity/py.typed
openbb_equity/shorts/__init__.py
openbb_equity/shorts/shorts_router.py
openbb_equity-1.4.1.dist-info/METADATA
openbb_equity-1.4.1.dist-info/WHEEL
openbb_equity-1.4.1.dist-info/entry_points.txt
openbb_equity-1.4.1.dist-info/RECORD
